{"_type":"export","__export_format":4,"__export_date":"2021-12-05T08:53:50.441Z","__export_source":"insomnia.desktop.app:v2021.6.0","resources":[{"_id":"req_2589bbeb6dcf4eefb667b7e8ebf42212","parentId":"fld_75caf5216520429d9e959ca6e48da7e3","modified":1638690446296,"created":1638495759381,"url":"{{ _.baseUrl }}/favorites","name":"Create favorite","description":"","method":"POST","body":{"mimeType":"application/json","text":"{\n\"Title\": \"Teste\",\n\"Year\": \"2005\",\n\"imdbID\": \"tt037278411aaaaaaaaaa\",\n\"Type\": \"movie\",\n\"Poster\": \"https://m.media-amazon.com/images/M/MV5BOTY4YjI2N2MtYmFlMC00ZjcyLTg3YjEtMDQyM2ZjYzQ5YWFkXkEyXkFqcGdeQXVyMTQxNzMzNDI@._V1_SX300.jpg\"\n}"},"parameters":[{"id":"pair_24bb23b0732a4fed94bc8ceb3ef7df93","name":"username","value":"teste","description":"","disabled":true},{"id":"pair_c39abb3daef24f0a9f3b55766fb1d0a4","name":"email","value":"teste@teste","description":"","disabled":true}],"headers":[{"name":"Content-Type","value":"application/json","id":"pair_af5dfa2493a64286baa1d77456f6867c"}],"authentication":{},"metaSortKey":-1638312518413.5,"isPrivate":false,"settingStoreCookies":true,"settingSendCookies":true,"settingDisableRenderRequestBody":false,"settingEncodeUrl":true,"settingRebuildPath":true,"settingFollowRedirects":"global","_type":"request"},{"_id":"fld_75caf5216520429d9e959ca6e48da7e3","parentId":"fld_bbc76cc1462f4c92b6208663344c691c","modified":1638562620237,"created":1638562620237,"name":"Favorite","description":"","environment":{},"environmentPropertyOrder":null,"metaSortKey":-1638562620237,"_type":"request_group"},{"_id":"fld_bbc76cc1462f4c92b6208663344c691c","parentId":"wrk_e2957fcab275475aa01209b72b73b843","modified":1638562591759,"created":1638562591759,"name":"Fleye","description":"","environment":{},"environmentPropertyOrder":null,"metaSortKey":-1638562591759,"_type":"request_group"},{"_id":"wrk_e2957fcab275475aa01209b72b73b843","parentId":null,"modified":1638694355012,"created":1637206200200,"name":"Fleye","description":"","scope":"collection","_type":"workspace"},{"_id":"req_dbd2caa1b5024a178d6cbc412a842ed0","parentId":"fld_75caf5216520429d9e959ca6e48da7e3","modified":1638562626665,"created":1638495348552,"url":"{{ _.baseUrl }}/favorites","name":"Get Favorites","description":"","method":"GET","body":{},"parameters":[{"id":"pair_24bb23b0732a4fed94bc8ceb3ef7df93","name":"name","value":"batman","description":"","disabled":true}],"headers":[],"authentication":{},"metaSortKey":-1638312518363.5,"isPrivate":false,"settingStoreCookies":true,"settingSendCookies":true,"settingDisableRenderRequestBody":false,"settingEncodeUrl":true,"settingRebuildPath":true,"settingFollowRedirects":"global","_type":"request"},{"_id":"req_7002cc89077849329a18c17b4438ec34","parentId":"fld_75caf5216520429d9e959ca6e48da7e3","modified":1638659602823,"created":1638659577286,"url":"{{ _.baseUrl }}/favorites/61a989e7362fc6700d44fa46","name":"Delete Favorite","description":"","method":"DELETE","body":{},"parameters":[{"id":"pair_24bb23b0732a4fed94bc8ceb3ef7df93","name":"name","value":"batman","description":"","disabled":true}],"headers":[],"authentication":{},"metaSortKey":-1637791491652.75,"isPrivate":false,"settingStoreCookies":true,"settingSendCookies":true,"settingDisableRenderRequestBody":false,"settingEncodeUrl":true,"settingRebuildPath":true,"settingFollowRedirects":"global","_type":"request"},{"_id":"req_ba3b92394c9e4f9a8b768ba677c9c7ca","parentId":"fld_7aeb8f48baf949d7a19b77f72d97a7ae","modified":1638675659004,"created":1638466692262,"url":"{{ _.baseUrl }}/movies","name":"Get Movie","description":"","method":"GET","body":{},"parameters":[{"id":"pair_24bb23b0732a4fed94bc8ceb3ef7df93","name":"name","value":"super","description":"","disabled":false}],"headers":[],"authentication":{},"metaSortKey":-1638562578508,"isPrivate":false,"settingStoreCookies":true,"settingSendCookies":true,"settingDisableRenderRequestBody":false,"settingEncodeUrl":true,"settingRebuildPath":true,"settingFollowRedirects":"global","_type":"request"},{"_id":"fld_7aeb8f48baf949d7a19b77f72d97a7ae","parentId":"fld_bbc76cc1462f4c92b6208663344c691c","modified":1638562600295,"created":1638562600295,"name":"Movie","description":"","environment":{},"environmentPropertyOrder":null,"metaSortKey":-1638562600295,"_type":"request_group"},{"_id":"req_42ac4429eb5d441a993704a25b874d45","parentId":"fld_7aeb8f48baf949d7a19b77f72d97a7ae","modified":1638684144839,"created":1638461383054,"url":"{{ _.baseUrl }}/movies","name":"Create movie","description":"","method":"POST","body":{"mimeType":"application/json","text":"{\n   \"movies\":[\n     \t{\n\t\t\t\t\"Title\": \"Super Metroid\",\n\t\t\t\t\"Year\": \"1994\",\n\t\t\t\t\"imdbID\": \"tt0206330\",\n\t\t\t\t\"Type\": \"game\",\n\t\t\t\t\"Poster\": \"N/A\"\n\t\t\t}\n   ]\n}"},"parameters":[],"headers":[{"name":"Content-Type","value":"application/json","id":"pair_af5dfa2493a64286baa1d77456f6867c"}],"authentication":{},"metaSortKey":-1638562578458,"isPrivate":false,"settingStoreCookies":true,"settingSendCookies":true,"settingDisableRenderRequestBody":false,"settingEncodeUrl":true,"settingRebuildPath":true,"settingFollowRedirects":"global","_type":"request"},{"_id":"env_348ea90f9c48ef62ffa9e6499a916090c0457576","parentId":"wrk_e2957fcab275475aa01209b72b73b843","modified":1638562304124,"created":1637206200472,"name":"Base Environment","data":{},"dataPropertyOrder":{},"color":null,"isPrivate":false,"metaSortKey":1637206200472,"_type":"environment"},{"_id":"jar_348ea90f9c48ef62ffa9e6499a916090c0457576","parentId":"wrk_e2957fcab275475aa01209b72b73b843","modified":1637206200488,"created":1637206200488,"name":"Default Jar","cookies":[],"_type":"cookie_jar"},{"_id":"spc_56e521e2ee664bb99aa9ba0ac7e0c449","parentId":"wrk_e2957fcab275475aa01209b72b73b843","modified":1637206200205,"created":1637206200205,"fileName":"Tests","contents":"","contentType":"yaml","_type":"api_spec"},{"_id":"env_49473b63cb794b95bd74913d33c27f49","parentId":"env_348ea90f9c48ef62ffa9e6499a916090c0457576","modified":1638562462446,"created":1638562317688,"name":"Prod","data":{"baseUrl":"https://challenge-fleye.herokuapp.com"},"dataPropertyOrder":{"&":["baseUrl"]},"color":"#7d69cb","isPrivate":false,"metaSortKey":1638562317688,"_type":"environment"},{"_id":"env_b5372ab8d9f642a9b7e72dc628208447","parentId":"env_348ea90f9c48ef62ffa9e6499a916090c0457576","modified":1638562446082,"created":1638562336571,"name":"Dev","data":{"baseUrl":"http://localhost:3000"},"dataPropertyOrder":{"&":["baseUrl"]},"color":"#6de876","isPrivate":false,"metaSortKey":1638562336571,"_type":"environment"}]}